README.md
setup.py
srs/__init__.py
srs/startified_sample.py
srs.egg-info/PKG-INFO
srs.egg-info/SOURCES.txt
srs.egg-info/dependency_links.txt
srs.egg-info/top_level.txt