Metadata-Version: 2.1
Name: srs
Version: 0.0.2
Summary: Startied random sample from the dataframe
Home-page: https://github.com/vrreddy695/startifiedRS
Author: Venkatramireddy Koppula
Author-email: venkatrami.reddy@latentview.com
License: UNKNOWN
Platform: UNKNOWN
Classifier: Programming Language :: Python 
Classifier: License :: OSI Approved :: MIT License
Classifier: Operating System :: OS Independent
